polygon_cli/__init__.py
polygon_cli/colors.py
polygon_cli/config.py
polygon_cli/exceptions.py
polygon_cli/freemarker_parsers.py
polygon_cli/global_vars.py
polygon_cli/json_encoders.py
polygon_cli/local_file.py
polygon_cli/polygon_cli.py
polygon_cli/polygon_file.py
polygon_cli/polygon_html_parsers.py
polygon_cli/problem.py
polygon_cli/utils.py
polygon_cli/actions/__init__.py
polygon_cli/actions/add.py
polygon_cli/actions/commit.py
polygon_cli/actions/common.py
polygon_cli/actions/diff.py
polygon_cli/actions/gettest.py
polygon_cli/actions/import_package.py
polygon_cli/actions/init.py
polygon_cli/actions/list.py
polygon_cli/actions/package.py
polygon_cli/actions/samples.py
polygon_cli/actions/tag_problem.py
polygon_cli/actions/tag_solution.py
polygon_cli/actions/update.py
polygon_cli/actions/update_groups.py
polygon_cli/actions/update_info.py
polygon_cli-1.1.14.dist-info/LICENSE
polygon_cli-1.1.14.dist-info/METADATA
polygon_cli-1.1.14.dist-info/WHEEL
polygon_cli-1.1.14.dist-info/entry_points.txt
polygon_cli-1.1.14.dist-info/top_level.txt
polygon_cli-1.1.14.dist-info/RECORD
