Metadata-Version: 2.1
Name: polygon-cli
Version: 1.1.14
Summary: Commandline tool for polygon
Home-page: https://github.com/kunyavskiy/polygon-cli
Author: Pavel Kunyavskiy
Author-email: kunyavskiy@gmail.com
License: MIT
License-File: LICENSE
Requires-Dist: colorama
Requires-Dist: requests
Requires-Dist: prettytable
Requires-Dist: pyyaml
